{
    "required":  true,
    "package":  "net.nostalgia.mixin",
    "refmap":  "nostalgia-refmap.json",
    "compatibilityLevel":  "JAVA_21",
    "mixins":  [
                   "rd132211.RDMovementMixin",
                   "rd132211.PlayerItemSyncMixin",
                   "rd132211.ServerLevelSoundMixin",
                   "rd132211.RDBlockPlacementMixin",
                   "rd132211.EntityMixin",
                   "AlphaSoundMixin",
                   "alpha.AlphaServerValidationBypassMixin",
                   "alpha.AlphaEnvironmentProbeMixin",
                   "server.HologramBlockBreakMixin",
                   "server.HologramBlockPlaceMixin",
                   "server.AlphaBlockPlaceMixin",
                   "server.AlphaBlockChangeMixin",
                   "server.LegacyWeatherMixin",
                   "alpha.AlphaRenderSetupMixin",
                   "alpha.AlphaLevelTickMixin",
                   "alpha.AlphaNaturalSpawnerBypassMixin",
                   "alpha.AlphaWaterSoundsMixin",
                   "alpha.AlphaMobLootMixin",
                   "physics.LegacyPhysicsCombatMixin",
                   "physics.LegacyPhysicsFoodPropertiesMixin",
                   "physics.LegacyPhysicsPlayerMixin",
                   "physics.LegacyPhysicsExperienceMixin",
                   "physics.LegacyPhysicsOffhandMixin",
                   "physics.LegacyPhysicsMobAIMixin",
                   "physics.AlphaConsumableMixin",
                   "physics.LegacyPhysicsBoatMixin",
                   "physics.LegacyPhysicsChestMixin",
                   "physics.LegacyPhysicsChestEntityMixin",
                   "physics.LegacyPhysicsChestSoundMixin",
                   "physics.LegacyPhysicsDoorSoundMixin",
                   "physics.LegacyPhysicsFireMixin",
                   "physics.LegacyPhysicsTntMixin",
                   "physics.LegacyPhysicsFarmlandMixin",
                   "physics.LegacyPhysicsCropMixin",
                   "physics.AlphaBlockEntityTypeMixin",
                   "physics.LegacyPhysicsPanicGoalMixin",
                   "alpha.AlphaSeedMixin",
                   "alpha.GhostModeEntityMixin",
                   "alpha.AlphaNoCritMixin",
                   "ritual.RitualAnchorMixin",
                   "ritual.RitualBlockPlaceMixin",
                   "ritual.BeaconInteractMixin",
                   "ritual.TickRateManagerMixin",
                   "ritual.LevelShouldTickBlocksAtMixin",
                   "ritual.ServerLevelShouldTickBlocksAtMixin",
                   "ritual.ServerLevelTickChunkFreezeMixin",
                   "ritual.ServerChunkCacheSpawnFreezeMixin",
                   "ritual.ServerLevelBlockTicksFreezeMixin",
                   "alpha.AlphaBowMixin",
                   "inventory.CraftingMenuMixin",
                   "AlphaEntityStateMixin",
                   "AlphaBabyMobMixin",
                   "alpha.AlphaTerrainAdjustmentMixin",
                   "alpha.AlphaLadderGapMixin",
                   "ritual.SlowSwingMixin"
               ],
    "client":  [
                   "alpha.AlphaKeyboardMixin",
                   "alpha.AlphaFogMixin",
                   "alpha.AlphaPlayerBridgeMixin",
                   "alpha.AlphaLivingEntityTextureMixin",
                   "alpha.AlphaSkyMixin",
                   "alpha.AlphaWaterRendererMixin",
                   "alpha.AlphaSodiumWaterMixin",
                   "alpha.AlphaLightTextureMixin",
                   "alpha.AlphaSodiumLightMixin",
                   "alpha.AlphaHudElementsMixin",
                   "alpha.AlphaAbstractRecipeBookScreenMixin",
                   "alpha.AlphaSlotMixin",
                   "alpha.AlphaInventoryScreenMixin",
                   "alpha.AlphaWaterAirMixin",
                   "alpha.AbstractContainerScreenAccessor",
                   "alpha.AlphaCloudDistanceMixin",
                   "physics.AlphaChestRendererMixin",
                   "physics.LegacyPhysicsGameModeMixin",
                   "physics.AbstractContainerScreenAccessor",
                   "physics.SlotAccessor",
                   "WorldOpenFlowsMixin",
                   "rd132211.MinecraftMixin",
                   "rd132211.FogRendererMixin",
                   "rd132211.GuiMixin",
                   "rd132211.SkyRendererMixin",
                   "rd132211.SkyRenderStateMixin",
                   "rd132211.PlayerMixin",
                   "rd132211.KeyboardMixin",
                   "rd132211.ItemInHandRendererMixin",
                   "rd132211.LevelRendererMixin",
                   "rd132211.LevelEventHandlerMixin",
                   "rd132211.RdFlatCardinalMixin",
                   "rd132211.RdNoShadowMixin",
                   "rd132211.RdFullBrightEntityMixin",
                   "rd132211.RdFullBrightLightmapMixin",
                   "rd132211.RdSodiumAOMixin",
                   "rd132211.ClientLevelSoundMixin",
                   "ritual.FakeBeaconBeamMixin",
                   "ritual.ClientLevelDayTimeMixin",
                   "ritual.MinecraftCinematicMixin",
                   "client.RenderPipelinesMixin",
                   "client.WhiteoutInjectMixin",
                   "client.LevelRendererDepthMaskMixin",
                   "client.LevelRendererCloudResetMixin",
                   "client.ritual.EntityRenderDispatcherMixin",
                   "client.ritual.ClientLevelChunkHologramMixin",
                   "client.ritual.CloudSpeedMixin",
                   "client.ritual.MinecraftFrozenZoneMixin",
                   "client.ritual.ClientClockManagerFreezeMixin",
                   "client.ritual.LevelGameTimeFreezeMixin",
                   "client.ritual.LevelRainFieldAccessor",
                   "client.ritual.DeltaTrackerFreezeMixin",
                   "client.ritual.LevelRendererZoneTickMixin",
                   "client.ritual.ParticleAccessor",
                   "client.ritual.ParticleGroupTickFreezeMixin",
                   "client.ritual.ParticleEngineAddMixin",
                   "client.ritual.ClientLevelAnimateTickFreezeMixin",
                   "client.ritual.CloudRendererDepthMixin",
                   "client.frozen.SpriteContentsAccessor",
                   "client.frozen.SpriteLoaderAccessor",
                   "client.frozen.SpriteLoaderMixin",
                   "client.frozen.TextureAtlasMixin",
                   "client.frozen.sodium.BlockRendererMixin",
                   "client.frozen.sodium.DefaultFluidRendererMixin",
                   "client.frozen.FlameFeatureRendererMixin",
                   "client.frozen.SingleQuadParticleExtractMixin",
                   "client.GameRendererCrashFixMixin",
                   "client.LoadingOverlayMixin",
                   "alpha.AlphaEntityStepSoundMixin",
                   "client.AlphaBlockModelMixin",
                   "visual.BoatRenderStateMixin",
                   "visual.AbstractBoatRendererMixin",
                   "visual.LegacyVisualBoatModelMixin",
                   "client.ItemEntityRendererAlphaMixin",
                   "render.ForceSkyRenderMixin",
                   "client.TitleScreenMixin",
                   "client.LevelRendererAllChangedMixin",
                   "client.ritual.BossHealthOverlayMixin",
                   "client.ritual.ClientLevelAuraMixin",
                   "ritual.render.WeatherEffectRendererMixin",
                   "client.AvatarRendererMixin",
                   "client.LivingEntityRendererAccessor",
                   "client.ritual.ChannelAccessor",
                   "client.ritual.SoundEngineMixin",
                   "client.FPVHandRendererMixin",
                   "client.ritual.ClientLevelChunkSectionMixin"
               ],
    "injectors":  {
                      "defaultRequire":  1
                  }
}
